EAyd_veriOnisleme/EAyd_veriOnisleme.py
EAyd_veriOnisleme/__init__.py
EAyd_veriOnisleme-0.0.8.dist-info/METADATA
EAyd_veriOnisleme-0.0.8.dist-info/WHEEL
EAyd_veriOnisleme-0.0.8.dist-info/top_level.txt
EAyd_veriOnisleme-0.0.8.dist-info/RECORD
