Metadata-Version: 2.1
Name: EAyd-veriOnisleme
Version: 0.0.8
Summary: Veri önişleme aşamalarında sık kullanılan metotlar
Home-page: https://github.com/
Author: Emrah Aydemir
Author-email: aydemir.emrah23@gmail.com
Classifier: Programming Language :: Python :: 3
Classifier: License :: OSI Approved :: MIT License
Classifier: Operating System :: OS Independent
Requires-Python: >=3.5.5
Requires-Dist: numpy
Requires-Dist: keras
